sequences/__init__.py
sequences/admin.py
sequences/apps.py
sequences/locale/bg/LC_MESSAGES/django.mo
sequences/locale/bg/LC_MESSAGES/django.po
sequences/locale/cs/LC_MESSAGES/django.mo
sequences/locale/cs/LC_MESSAGES/django.po
sequences/locale/da/LC_MESSAGES/django.mo
sequences/locale/da/LC_MESSAGES/django.po
sequences/locale/de/LC_MESSAGES/django.mo
sequences/locale/de/LC_MESSAGES/django.po
sequences/locale/es/LC_MESSAGES/django.mo
sequences/locale/es/LC_MESSAGES/django.po
sequences/locale/fr/LC_MESSAGES/django.mo
sequences/locale/fr/LC_MESSAGES/django.po
sequences/locale/it/LC_MESSAGES/django.mo
sequences/locale/it/LC_MESSAGES/django.po
sequences/locale/ja/LC_MESSAGES/django.mo
sequences/locale/ja/LC_MESSAGES/django.po
sequences/locale/lt/LC_MESSAGES/django.mo
sequences/locale/lt/LC_MESSAGES/django.po
sequences/locale/nl/LC_MESSAGES/django.mo
sequences/locale/nl/LC_MESSAGES/django.po
sequences/locale/pt/LC_MESSAGES/django.mo
sequences/locale/pt/LC_MESSAGES/django.po
sequences/locale/rm/LC_MESSAGES/django.mo
sequences/locale/rm/LC_MESSAGES/django.po
sequences/locale/ru/LC_MESSAGES/django.mo
sequences/locale/ru/LC_MESSAGES/django.po
sequences/locale/sk/LC_MESSAGES/django.mo
sequences/locale/sk/LC_MESSAGES/django.po
sequences/locale/sv/LC_MESSAGES/django.mo
sequences/locale/sv/LC_MESSAGES/django.po
sequences/locale/th/LC_MESSAGES/django.mo
sequences/locale/th/LC_MESSAGES/django.po
sequences/locale/tr/LC_MESSAGES/django.mo
sequences/locale/tr/LC_MESSAGES/django.po
sequences/migrations/0001_initial.py
sequences/migrations/0002_alter_sequence_last.py
sequences/migrations/__init__.py
sequences/models.py
django_sequences-2.9.dist-info/LICENSE
django_sequences-2.9.dist-info/METADATA
django_sequences-2.9.dist-info/WHEEL
django_sequences-2.9.dist-info/RECORD
